apitools/__init__.py
apitools/base/__init__.py
apitools/base/protorpclite/__init__.py
apitools/base/protorpclite/descriptor.py
apitools/base/protorpclite/message_types.py
apitools/base/protorpclite/messages.py
apitools/base/protorpclite/protojson.py
apitools/base/protorpclite/util.py
apitools/base/py/__init__.py
apitools/base/py/base_api.py
apitools/base/py/batch.py
apitools/base/py/buffered_stream.py
apitools/base/py/compression.py
apitools/base/py/credentials_lib.py
apitools/base/py/encoding.py
apitools/base/py/encoding_helper.py
apitools/base/py/exceptions.py
apitools/base/py/extra_types.py
apitools/base/py/gzip.py
apitools/base/py/http_wrapper.py
apitools/base/py/list_pager.py
apitools/base/py/stream_slice.py
apitools/base/py/transfer.py
apitools/base/py/util.py
apitools/data/__init__.py
apitools/data/apitools_client_secrets.json
apitools/gen/__init__.py
apitools/gen/extended_descriptor.py
apitools/gen/gen_client.py
apitools/gen/gen_client_lib.py
apitools/gen/message_registry.py
apitools/gen/service_registry.py
apitools/gen/util.py
apitools/scripts/__init__.py
google_apitools-0.5.29.dist-info/LICENSE
google_apitools-0.5.29.dist-info/METADATA
google_apitools-0.5.29.dist-info/WHEEL
google_apitools-0.5.29.dist-info/entry_points.txt
google_apitools-0.5.29.dist-info/top_level.txt
google_apitools-0.5.29.dist-info/RECORD
