Metadata-Version: 2.1
Name: google-apitools
Version: 0.5.29
Summary: client libraries for humans
Home-page: http://github.com/google/apitools
Author: Craig Citro
Author-email: craigcitro@google.com
License: Apache 2.0
Keywords: apitools
Platform: UNKNOWN
Classifier: License :: OSI Approved :: Apache Software License
Classifier: Topic :: Software Development :: Libraries
Classifier: Topic :: Software Development :: Libraries :: Python Modules
Requires-Dist: httplib2 (>=0.8)
Requires-Dist: fasteners (>=0.14)
Requires-Dist: oauth2client (>=1.4.12)
Requires-Dist: six (>=1.12.0)
Provides-Extra: cli
Requires-Dist: python-gflags (>=3.0.6) ; extra == 'cli'
Provides-Extra: testing
Requires-Dist: unittest2 (>=0.5.1) ; extra == 'testing'
Requires-Dist: mock (>=1.0.1) ; extra == 'testing'
